x16r_hash.cp36-win_amd64.pyd
x16r_hash-1.0.1.dist-info/METADATA
x16r_hash-1.0.1.dist-info/RECORD
x16r_hash-1.0.1.dist-info/WHEEL
x16r_hash-1.0.1.dist-info/top_level.txt
